{"commontoolconfiguration_elasticsearch_elasticsearch.7x.md":"CfG4P_yW","commontoolconfiguration_mysql_mysql.md":"BzPsKTNm","commontoolconfiguration_mysql_mysql_code.md":"DiQOEqk-","commontoolconfiguration_nfs_nfs.md":"CTpTg5fN","commontoolconfiguration_nginx_nginx.md":"0ChmWJxq","commontoolconfiguration_php_php.md":"CJZsDod7","commontoolconfiguration_shell_common.md":"BCXtgbiy","languagelearning_python_index.md":"D92zI6-Z","api-examples.md":"icvJMdhU","api_authapipay_api_doc.md":"Cvo5EQT6","index.md":"C8NGMb9Q","markdown-examples.md":"fW3VtnmZ","other_cdn_cloudflare.md":"BAes-t0k","other_frame_wordpress.md":"FwQMCvFC","other_google_google配置.md":"ali9kPmI","other_linux_unbutu2204.md":"RfAYHyo1","other_mac_mac_system.md":"GcVlik2R","other_ssl_selfsignedssl.md":"C1pSp2Z6","other_tools_create-dmg.md":"sAlJa2ap","other_tools_keystore.md":"DGPM7_rc","other_tools_webclip.md":"DdqN6sTu","tools_webstorm.md":"C7RnNovE"}
